[{"type": "WatchEvent", "public": true, "payload": "{\"action\":\"started\"}", "repo": {"id": 177417757, "name": "lfortran/lfortran", "url": "https://api.github.com/repos/lfortran/lfortran"}, "actor": {"id": 3787206, "login": "quepas", "gravatar_id": "", "avatar_url": "https://avatars.githubusercontent.com/u/3787206?", "url": "https://api.github.com/users/quepas"}, "org": {"id": 40613057, "login": "lfortran", "gravatar_id": "", "avatar_url": "https://avatars.githubusercontent.com/u/40613057?", "url": "https://api.github.com/orgs/lfortran"}, "created_at": 1725880246000, "id": "41747796518", "other": "{\"actor\":{\"display_login\":\"quepas\"}}"}, {"type": "WatchEvent", "public": true, "payload": "{\"action\":\"started\"}", "repo": {"id": 412392321, "name": "fortran-lang/fortls", "url": "https://api.github.com/repos/fortran-lang/fortls"}, "actor": {"id": 3787206, "login": "quepas", "gravatar_id": "", "avatar_url": "https://avatars.githubusercontent.com/u/3787206?", "url": "https://api.github.com/users/quepas"}, "org": {"id": 53436240, "login": "fortran-lang", "gravatar_id": "", "avatar_url": "https://avatars.githubusercontent.com/u/53436240?", "url": "https://api.github.com/orgs/fortran-lang"}, "created_at": 1685707213000, "id": "29488874673", "other": "{\"actor\":{\"display_login\":\"quepas\"}}"}]