[{"type": "WatchEvent", "public": true, "payload": "{\"action\":\"started\"}", "repo": {"id": 295937092, "name": "gnu-octave/octave", "url": "https://api.github.com/repos/gnu-octave/octave"}, "actor": {"id": 175263029, "login": "2gab", "gravatar_id": "", "avatar_url": "https://avatars.githubusercontent.com/u/175263029?", "url": "https://api.github.com/users/2gab"}, "org": {"id": 5480630, "login": "gnu-octave", "gravatar_id": "", "avatar_url": "https://avatars.githubusercontent.com/u/5480630?", "url": "https://api.github.com/orgs/gnu-octave"}, "created_at": 1734116137000, "id": "44775562264", "other": "{\"actor\":{\"display_login\":\"2gab\"}}"}, {"type": "WatchEvent", "public": true, "payload": "{\"action\":\"started\"}", "repo": {"id": 908607, "name": "numpy/numpy", "url": "https://api.github.com/repos/numpy/numpy"}, "actor": {"id": 175263029, "login": "2gab", "gravatar_id": "", "avatar_url": "https://avatars.githubusercontent.com/u/175263029?", "url": "https://api.github.com/users/2gab"}, "org": {"id": 288276, "login": "numpy", "gravatar_id": "", "avatar_url": "https://avatars.githubusercontent.com/u/288276?", "url": "https://api.github.com/orgs/numpy"}, "created_at": 1728308773000, "id": "42608640822", "other": "{\"actor\":{\"display_login\":\"2gab\"}}"}, {"type": "WatchEvent", "public": true, "payload": "{\"action\":\"started\"}", "repo": {"id": 228099010, "name": "fortran-lang/stdlib", "url": "https://api.github.com/repos/fortran-lang/stdlib"}, "actor": {"id": 175263029, "login": "2gab", "gravatar_id": "", "avatar_url": "https://avatars.githubusercontent.com/u/175263029?", "url": "https://api.github.com/users/2gab"}, "org": {"id": 53436240, "login": "fortran-lang", "gravatar_id": "", "avatar_url": "https://avatars.githubusercontent.com/u/53436240?", "url": "https://api.github.com/orgs/fortran-lang"}, "created_at": 1728309633000, "id": "42609258157", "other": "{\"actor\":{\"display_login\":\"2gab\"}}"}, {"type": "WatchEvent", "public": true, "payload": "{\"action\":\"started\"}", "repo": {"id": 843222, "name": "scikit-learn/scikit-learn", "url": "https://api.github.com/repos/scikit-learn/scikit-learn"}, "actor": {"id": 175263029, "login": "2gab", "gravatar_id": "", "avatar_url": "https://avatars.githubusercontent.com/u/175263029?", "url": "https://api.github.com/users/2gab"}, "org": {"id": 365630, "login": "scikit-learn", "gravatar_id": "", "avatar_url": "https://avatars.githubusercontent.com/u/365630?", "url": "https://api.github.com/orgs/scikit-learn"}, "created_at": 1728492595000, "id": "42696488566", "other": "{\"actor\":{\"display_login\":\"2gab\"}}"}, {"type": "WatchEvent", "public": true, "payload": "{\"action\":\"started\"}", "repo": {"id": 1385122, "name": "matplotlib/matplotlib", "url": "https://api.github.com/repos/matplotlib/matplotlib"}, "actor": {"id": 133578283, "login": "2gab", "gravatar_id": "", "avatar_url": "https://avatars.githubusercontent.com/u/133578283?", "url": "https://api.github.com/users/2gab"}, "org": {"id": 215947, "login": "matplotlib", "gravatar_id": "", "avatar_url": "https://avatars.githubusercontent.com/u/215947?", "url": "https://api.github.com/orgs/matplotlib"}, "created_at": 1716226830000, "id": "38540723168", "other": "{\"actor\":{\"display_login\":\"2gab\"}}"}, {"type": "WatchEvent", "public": true, "payload": "{\"action\":\"started\"}", "repo": {"id": 858127, "name": "pandas-dev/pandas", "url": "https://api.github.com/repos/pandas-dev/pandas"}, "actor": {"id": 133578283, "login": "2gab", "gravatar_id": "", "avatar_url": "https://avatars.githubusercontent.com/u/133578283?", "url": "https://api.github.com/users/2gab"}, "org": {"id": 21206976, "login": "pandas-dev", "gravatar_id": "", "avatar_url": "https://avatars.githubusercontent.com/u/21206976?", "url": "https://api.github.com/orgs/pandas-dev"}, "created_at": 1716227699000, "id": "38541105959", "other": "{\"actor\":{\"display_login\":\"2gab\"}}"}, {"type": "WatchEvent", "public": true, "payload": "{\"action\":\"started\"}", "repo": {"id": 858127, "name": "pandas-dev/pandas", "url": "https://api.github.com/repos/pandas-dev/pandas"}, "actor": {"id": 133578283, "login": "2gab", "gravatar_id": "", "avatar_url": "https://avatars.githubusercontent.com/u/133578283?", "url": "https://api.github.com/users/2gab"}, "org": {"id": 21206976, "login": "pandas-dev", "gravatar_id": "", "avatar_url": "https://avatars.githubusercontent.com/u/21206976?", "url": "https://api.github.com/orgs/pandas-dev"}, "created_at": 1716227754000, "id": "38541128666", "other": "{\"actor\":{\"display_login\":\"2gab\"}}"}]