[{"type": "ForkEvent", "public": true, "payload": "{\"forkee\":{\"id\":866151350,\"node_id\":\"R_kgDOM6Brtg\",\"name\":\"numpy.github.com\",\"full_name\":\"karhdz89/numpy.github.com\",\"private\":false,\"public\":true}}", "repo": {"id": 3376070, "name": "numpy/numpy.github.com", "url": "https://api.github.com/repos/numpy/numpy.github.com"}, "actor": {"id": 183461519, "login": "karhdz89", "gravatar_id": "", "avatar_url": "https://avatars.githubusercontent.com/u/183461519?", "url": "https://api.github.com/users/karhdz89"}, "org": {"id": 288276, "login": "numpy", "gravatar_id": "", "avatar_url": "https://avatars.githubusercontent.com/u/288276?", "url": "https://api.github.com/orgs/numpy"}, "created_at": 1727807121000, "id": "42448015983", "other": "{\"actor\":{\"display_login\":\"karhdz89\"}}"}, {"type": "ForkEvent", "public": true, "payload": "{\"forkee\":{\"id\":866153589,\"node_id\":\"R_kgDOM6B0dQ\",\"name\":\"numpy\",\"full_name\":\"karhdz89/numpy\",\"private\":false,\"public\":true}}", "repo": {"id": 908607, "name": "numpy/numpy", "url": "https://api.github.com/repos/numpy/numpy"}, "actor": {"id": 183461519, "login": "karhdz89", "gravatar_id": "", "avatar_url": "https://avatars.githubusercontent.com/u/183461519?", "url": "https://api.github.com/users/karhdz89"}, "org": {"id": 288276, "login": "numpy", "gravatar_id": "", "avatar_url": "https://avatars.githubusercontent.com/u/288276?", "url": "https://api.github.com/orgs/numpy"}, "created_at": 1727807384000, "id": "42448147026", "other": "{\"actor\":{\"display_login\":\"karhdz89\"}}"}]