[{"type": "ForkEvent", "public": true, "payload": "{\"forkee\":{\"id\":875236709,\"node_id\":\"R_kgDONCsNZQ\",\"name\":\"numpy\",\"full_name\":\"Rahul-Ram-03/numpy\",\"private\":false,\"public\":true}}", "repo": {"id": 908607, "name": "numpy/numpy", "url": "https://api.github.com/repos/numpy/numpy"}, "actor": {"id": 79851438, "login": "Rahul-Ram-03", "gravatar_id": "", "avatar_url": "https://avatars.githubusercontent.com/u/79851438?", "url": "https://api.github.com/users/Rahul-Ram-03"}, "org": {"id": 288276, "login": "numpy", "gravatar_id": "", "avatar_url": "https://avatars.githubusercontent.com/u/288276?", "url": "https://api.github.com/orgs/numpy"}, "created_at": 1729342801000, "id": "43006760425", "other": "{\"actor\":{\"display_login\":\"Rahul-Ram-03\"}}"}, {"type": "ForkEvent", "public": true, "payload": "{\"forkee\":{\"id\":523820711,\"node_id\":\"R_kgDOHzjepw\",\"name\":\"pandas\",\"full_name\":\"Rahul-Ram-03/pandas\",\"private\":false,\"owner\":{\"login\":\"Rahul-Ram-03\",\"id\":79851438,\"node_id\":\"MDQ6VXNlcjc5ODUxNDM4\",\"avatar_url\":\"https://avatars.githubusercontent.com/u/79851438?v=4\",\"gravatar_id\":\"\",\"url\":\"https://api.github.com/users/Rahul-Ram-03\",\"html_url\":\"https://github.com/Rahul-Ram-03\",\"followers_url\":\"https://api.github.com/users/Rahul-Ram-03/followers\",\"following_url\":\"https://api.github.com/users/Rahul-Ram-03/following{/other_user}\",\"gists_url\":\"https://api.github.com/users/Rahul-Ram-03/gists{/gist_id}\",\"starred_url\":\"https://api.github.com/users/Rahul-Ram-03/starred{/owner}{/repo}\",\"subscriptions_url\":\"https://api.github.com/users/Rahul-Ram-03/subscriptions\",\"organizations_url\":\"https://api.github.com/users/Rahul-Ram-03/orgs\",\"repos_url\":\"https://api.github.com/users/Rahul-Ram-03/repos\",\"events_url\":\"https://api.github.com/users/Rahul-Ram-03/events{/privacy}\",\"received_events_url\":\"https://api.github.com/users/Rahul-Ram-03/received_events\",\"type\":\"User\",\"site_admin\":false},\"html_url\":\"https://github.com/Rahul-Ram-03/pandas\",\"description\":\"Flexible and powerful data analysis / manipulation library for Python, providing labeled data structures similar to R data.frame objects, statistical functions, and much more\",\"fork\":true,\"url\":\"https://api.github.com/repos/Rahul-Ram-03/pandas\",\"forks_url\":\"https://api.github.com/repos/Rahul-Ram-03/pandas/forks\",\"keys_url\":\"https://api.github.com/repos/Rahul-Ram-03/pandas/keys{/key_id}\",\"collaborators_url\":\"https://api.github.com/repos/Rahul-Ram-03/pandas/collaborators{/collaborator}\",\"teams_url\":\"https://api.github.com/repos/Rahul-Ram-03/pandas/teams\",\"hooks_url\":\"https://api.github.com/repos/Rahul-Ram-03/pandas/hooks\",\"issue_events_url\":\"https://api.github.com/repos/Rahul-Ram-03/pandas/issues/events{/number}\",\"events_url\":\"https://api.github.com/repos/Rahul-Ram-03/pandas/events\",\"assignees_url\":\"https://api.github.com/repos/Rahul-Ram-03/pandas/assignees{/user}\",\"branches_url\":\"https://api.github.com/repos/Rahul-Ram-03/pandas/branches{/branch}\",\"tags_url\":\"https://api.github.com/repos/Rahul-Ram-03/pandas/tags\",\"blobs_url\":\"https://api.github.com/repos/Rahul-Ram-03/pandas/git/blobs{/sha}\",\"git_tags_url\":\"https://api.github.com/repos/Rahul-Ram-03/pandas/git/tags{/sha}\",\"git_refs_url\":\"https://api.github.com/repos/Rahul-Ram-03/pandas/git/refs{/sha}\",\"trees_url\":\"https://api.github.com/repos/Rahul-Ram-03/pandas/git/trees{/sha}\",\"statuses_url\":\"https://api.github.com/repos/Rahul-Ram-03/pandas/statuses/{sha}\",\"languages_url\":\"https://api.github.com/repos/Rahul-Ram-03/pandas/languages\",\"stargazers_url\":\"https://api.github.com/repos/Rahul-Ram-03/pandas/stargazers\",\"contributors_url\":\"https://api.github.com/repos/Rahul-Ram-03/pandas/contributors\",\"subscribers_url\":\"https://api.github.com/repos/Rahul-Ram-03/pandas/subscribers\",\"subscription_url\":\"https://api.github.com/repos/Rahul-Ram-03/pandas/subscription\",\"commits_url\":\"https://api.github.com/repos/Rahul-Ram-03/pandas/commits{/sha}\",\"git_commits_url\":\"https://api.github.com/repos/Rahul-Ram-03/pandas/git/commits{/sha}\",\"comments_url\":\"https://api.github.com/repos/Rahul-Ram-03/pandas/comments{/number}\",\"issue_comment_url\":\"https://api.github.com/repos/Rahul-Ram-03/pandas/issues/comments{/number}\",\"contents_url\":\"https://api.github.com/repos/Rahul-Ram-03/pandas/contents/{+path}\",\"compare_url\":\"https://api.github.com/repos/Rahul-Ram-03/pandas/compare/{base}...{head}\",\"merges_url\":\"https://api.github.com/repos/Rahul-Ram-03/pandas/merges\",\"archive_url\":\"https://api.github.com/repos/Rahul-Ram-03/pandas/{archive_format}{/ref}\",\"downloads_url\":\"https://api.github.com/repos/Rahul-Ram-03/pandas/downloads\",\"issues_url\":\"https://api.github.com/repos/Rahul-Ram-03/pandas/issues{/number}\",\"pulls_url\":\"https://api.github.com/repos/Rahul-Ram-03/pandas/pulls{/number}\",\"milestones_url\":\"https://api.github.com/repos/Rahul-Ram-03/pandas/milestones{/number}\",\"notifications_url\":\"https://api.github.com/repos/Rahul-Ram-03/pandas/notifications{?since,all,participating}\",\"labels_url\":\"https://api.github.com/repos/Rahul-Ram-03/pandas/labels{/name}\",\"releases_url\":\"https://api.github.com/repos/Rahul-Ram-03/pandas/releases{/id}\",\"deployments_url\":\"https://api.github.com/repos/Rahul-Ram-03/pandas/deployments\",\"created_at\":\"2022-08-11T17:59:50Z\",\"updated_at\":\"2022-08-11T17:48:04Z\",\"pushed_at\":\"2022-08-11T17:32:17Z\",\"git_url\":\"git://github.com/Rahul-Ram-03/pandas.git\",\"ssh_url\":\"git@github.com:Rahul-Ram-03/pandas.git\",\"clone_url\":\"https://github.com/Rahul-Ram-03/pandas.git\",\"svn_url\":\"https://github.com/Rahul-Ram-03/pandas\",\"homepage\":\"https://pandas.pydata.org\",\"size\":278982,\"stargazers_count\":0,\"watchers_count\":0,\"language\":null,\"has_issues\":false,\"has_projects\":true,\"has_downloads\":true,\"has_wiki\":false,\"has_pages\":false,\"forks_count\":0,\"mirror_url\":null,\"archived\":false,\"disabled\":false,\"open_issues_count\":0,\"license\":null,\"allow_forking\":true,\"is_template\":false,\"web_commit_signoff_required\":false,\"topics\":[],\"visibility\":\"public\",\"forks\":0,\"open_issues\":0,\"watchers\":0,\"default_branch\":\"main\",\"public\":true}}", "repo": {"id": 858127, "name": "pandas-dev/pandas", "url": "https://api.github.com/repos/pandas-dev/pandas"}, "actor": {"id": 79851438, "login": "Rahul-Ram-03", "gravatar_id": "", "avatar_url": "https://avatars.githubusercontent.com/u/79851438?", "url": "https://api.github.com/users/Rahul-Ram-03"}, "org": {"id": 21206976, "login": "pandas-dev", "gravatar_id": "", "avatar_url": "https://avatars.githubusercontent.com/u/21206976?", "url": "https://api.github.com/orgs/pandas-dev"}, "created_at": 1660240791000, "id": "23391174307", "other": "{\"actor\":{\"display_login\":\"Rahul-Ram-03\"}}"}]