[{"type": "WatchEvent", "public": true, "payload": "{\"action\":\"started\"}", "repo": {"id": 908607, "name": "numpy/numpy", "url": "https://api.github.com/repos/numpy/numpy"}, "actor": {"id": 132875570, "login": "tay-byotik", "gravatar_id": "", "avatar_url": "https://avatars.githubusercontent.com/u/132875570?", "url": "https://api.github.com/users/tay-byotik"}, "org": {"id": 288276, "login": "numpy", "gravatar_id": "", "avatar_url": "https://avatars.githubusercontent.com/u/288276?", "url": "https://api.github.com/orgs/numpy"}, "created_at": 1727518496000, "id": "42356079438", "other": "{\"actor\":{\"display_login\":\"tay-byotik\"}}"}]