[{"type": "WatchEvent", "public": true, "payload": "{\"action\":\"started\"}", "repo": {"id": 72523920, "name": "cupy/cupy", "url": "https://api.github.com/repos/cupy/cupy"}, "actor": {"id": 365334, "login": "argoneus", "gravatar_id": "", "avatar_url": "https://avatars.githubusercontent.com/u/365334?", "url": "https://api.github.com/users/argoneus"}, "org": {"id": 23187665, "login": "cupy", "gravatar_id": "", "avatar_url": "https://avatars.githubusercontent.com/u/23187665?", "url": "https://api.github.com/orgs/cupy"}, "created_at": 1726860356000, "id": "42129245637", "other": "{\"actor\":{\"display_login\":\"argoneus\"}}"}]